LICENSE.txt
MANIFEST.in
README.md
setup.cfg
setup.py
blurlab/BoxBlur.py
blurlab/DefocusBlur.py
blurlab/GaussianBlur.py
blurlab/LineDictionary.py
blurlab/LinearMotionBlur.py
blurlab/PsfBlur.py
blurlab/RandomizedBlur.py
blurlab/__init__.py
blurlab/psf.pkl
blurlab.egg-info/PKG-INFO
blurlab.egg-info/SOURCES.txt
blurlab.egg-info/dependency_links.txt
blurlab.egg-info/requires.txt
blurlab.egg-info/top_level.txt
blurlab.egg-info/.ipynb_checkpoints/PKG-INFO-checkpoint
blurlab.egg-info/.ipynb_checkpoints/SOURCES-checkpoint.txt
blurlab.egg-info/.ipynb_checkpoints/dependency_links-checkpoint.txt
blurlab.egg-info/.ipynb_checkpoints/top_level-checkpoint.txt