Metadata-Version: 2.1
Name: blurlab
Version: 0.3
Summary: Fix some issues from pyblur
Home-page: https://github.com/jayroxis/blurlab
Author: jayroxis
Author-email: bujie314@gmail.com
License: MIT
Download-URL: https://github.com/jayroxis/blurlab/archive/refs/tags/v0.1.0.tar.gz
Keywords: blur,image,cv,vision,processing,convolution
Platform: UNKNOWN
Classifier: Development Status :: 3 - Alpha
Classifier: Intended Audience :: Developers
Classifier: Topic :: Software Development :: Build Tools
Classifier: License :: OSI Approved :: MIT License
Classifier: Programming Language :: Python :: 3
Classifier: Programming Language :: Python :: 3.4
Classifier: Programming Language :: Python :: 3.5
Classifier: Programming Language :: Python :: 3.6
Requires-Python: >=3
